{
    "entries": [
        {
            "date": "2020-08-17",
            "content": "it fuckin worked again lol"
        },
        {
            "date": "2020-08-17",
            "content": "it fuckin worked lol"
        },
        {
            "date": "2020-08-17",
            "content": "does it work??"
        },
        {
            "date": "2020-08-17",
            "content": "cmon work"
        },
        {
            "date": "2020-08-17 01:25 AM",
            "content": "cmon work plz"
        },
        {
            "date": "2020-08-17 01:27 AM",
            "content": "cmon work plz2"
        },
        {
            "date": "2020-08-17 01:31 AM",
            "content": "test"
        },
        {
            "date": "2020-08-21 04:48 AM",
            "content": "I made this page look a hell of a lot better"
        }
    ]
}